[
    {
        "name": "deposit",
        "type": "function",
        "inputs": [
        {
            "name": "token",
            "type": "core::starknet::contract_address::ContractAddress"
        },
        {
            "name": "amount",
            "type": "core::felt252"
        }
        ],
        "outputs": [],
        "state_mutability": "external"
    },
    {
        "name": "withdraw",
        "type": "function",
        "inputs": [
        {
            "name": "token",
            "type": "core::starknet::contract_address::ContractAddress"
        },
        {
            "name": "amount",
            "type": "core::felt252"
        }
        ],
        "outputs": [],
        "state_mutability": "external"
    },
    {
        "name": "withdraw_all",
        "type": "function",
        "inputs": [
        {
            "name": "token",
            "type": "core::starknet::contract_address::ContractAddress"
        }
        ],
        "outputs": [],
        "state_mutability": "external"
    }
]